[
  {
    "line": 1,
    "elements": [
      {
        "line": 4,
        "name": "check admin details",
        "description": "",
        "id": "test-admin-details;check-admin-details",
        "type": "scenario",
        "keyword": "Scenario",
        "steps": [
          {
            "result": {
              "duration": 55088400,
              "status": "passed"
            },
            "line": 5,
            "name": "open Admin_deatils Page",
            "match": {
              "location": "StepDefinitions.open_Admin_deatils_Page()"
            },
            "keyword": "Given "
          },
          {
            "result": {
              "duration": 23200,
              "status": "passed"
            },
            "line": 7,
            "name": "click on Admin_Info button",
            "match": {
              "location": "StepDefinitions.click_on_Admin_Info_button()"
            },
            "keyword": "When "
          },
          {
            "result": {
              "duration": 1099600,
              "status": "passed"
            },
            "line": 8,
            "name": "should redirect to Admin Info page",
            "match": {
              "location": "StepDefinitions.should_redirect_to_Admin_Info_page()"
            },
            "keyword": "Then "
          }
        ]
      }
    ],
    "name": "Test Admin details",
    "description": "",
    "id": "test-admin-details",
    "keyword": "Feature",
    "uri": "Admin_Info.feature"
  },
  {
    "line": 1,
    "name": "Test Finance Info",
    "description": "",
    "id": "test-finance-info",
    "keyword": "Feature",
    "uri": "Finance_info.feature"
  },
  {
    "line": 1,
    "elements": [
      {
        "line": 4,
        "name": "test functionality of Home_page",
        "description": "",
        "id": "test-home-page;test-functionality-of-home-page",
        "type": "scenario",
        "keyword": "Scenario",
        "steps": [
          {
            "result": {
              "duration": 14100,
              "status": "passed"
            },
            "line": 5,
            "name": "open login Page",
            "match": {
              "location": "StepDefinitions.open_login_Page()"
            },
            "keyword": "Given "
          },
          {
            "result": {
              "duration": 9400,
              "status": "passed"
            },
            "line": 6,
            "name": "enter login credentials",
            "match": {
              "location": "StepDefinitions.enter_login_credentials()"
            },
            "keyword": "And "
          },
          {
            "result": {
              "duration": 8200,
              "status": "passed"
            },
            "line": 7,
            "name": "click on login",
            "match": {
              "location": "StepDefinitions.click_on_login()"
            },
            "keyword": "When "
          },
          {
            "result": {
              "duration": 12800,
              "status": "passed"
            },
            "line": 10,
            "name": "should redirect Home page",
            "match": {
              "location": "StepDefinitions.should_redirect_Home_page()"
            },
            "keyword": "Then "
          }
        ]
      }
    ],
    "name": "Test Home_page",
    "description": "",
    "id": "test-home-page",
    "keyword": "Feature",
    "uri": "TestHomepage.feature"
  },
  {
    "line": 1,
    "elements": [
      {
        "line": 4,
        "name": "check client details",
        "description": "",
        "id": "test-client-info;check-client-details",
        "type": "scenario",
        "keyword": "Scenario",
        "steps": [
          {
            "result": {
              "duration": 16900,
              "status": "passed"
            },
            "line": 5,
            "name": "open Client_deatils Page",
            "match": {
              "location": "StepDefinitions.open_Client_deatils_Page()"
            },
            "keyword": "Given "
          },
          {
            "result": {
              "duration": 8300,
              "status": "passed"
            },
            "line": 7,
            "name": "click on client_Info button",
            "match": {
              "location": "StepDefinitions.click_on_client_Info_button()"
            },
            "keyword": "When "
          },
          {
            "result": {
              "duration": 355600,
              "error_message": "org.testng.SkipException: skipped\r\n\tat com.Test.EO.StepDefinitions.should_redirect_to_client_Info_page(StepDefinitions.java:113)\r\n\tat ✽.Then should redirect to client Info page(client_info.feature:8)\r\n",
              "status": "failed"
            },
            "line": 8,
            "name": "should redirect to client Info page",
            "match": {
              "location": "StepDefinitions.should_redirect_to_client_Info_page()"
            },
            "keyword": "Then "
          }
        ]
      }
    ],
    "name": "Test Client Info",
    "description": "",
    "id": "test-client-info",
    "keyword": "Feature",
    "uri": "client_info.feature"
  },
  {
    "line": 1,
    "elements": [
      {
        "line": 4,
        "name": "check company details",
        "description": "",
        "id": "test-company-details;check-company-details",
        "type": "scenario",
        "keyword": "Scenario",
        "steps": [
          {
            "result": {
              "duration": 23900,
              "status": "passed"
            },
            "line": 5,
            "name": "open company_deatils Page",
            "match": {
              "location": "StepDefinitions.open_company_deatils_Page()"
            },
            "keyword": "Given "
          },
          {
            "result": {
              "duration": 14200,
              "status": "passed"
            },
            "line": 7,
            "name": "click on company_Info button",
            "match": {
              "location": "StepDefinitions.click_on_company_Info_button()"
            },
            "keyword": "When "
          },
          {
            "result": {
              "duration": 14400,
              "status": "passed"
            },
            "line": 8,
            "name": "should redirect to company Info page",
            "match": {
              "location": "StepDefinitions.should_redirect_to_company_Info_page()"
            },
            "keyword": "Then "
          }
        ]
      }
    ],
    "name": "Test company details",
    "description": "",
    "id": "test-company-details",
    "keyword": "Feature",
    "uri": "company_info.feature"
  },
  {
    "line": 1,
    "elements": [
      {
        "line": 4,
        "name": "check customer details",
        "description": "",
        "id": "test-customer-details;check-customer-details",
        "type": "scenario",
        "keyword": "Scenario",
        "steps": [
          {
            "result": {
              "duration": 36600,
              "status": "passed"
            },
            "line": 5,
            "name": "open customer_deatils Page",
            "match": {
              "location": "StepDefinitions.open_customer_deatils_Page()"
            },
            "keyword": "Given "
          },
          {
            "result": {
              "duration": 11300,
              "status": "passed"
            },
            "line": 7,
            "name": "click on customer_Info button",
            "match": {
              "location": "StepDefinitions.click_on_customer_Info_button()"
            },
            "keyword": "When "
          },
          {
            "result": {
              "duration": 605800,
              "error_message": "java.lang.AssertionError: expected [true] but found [false]\r\n\tat org.testng.Assert.fail(Assert.java:96)\r\n\tat org.testng.Assert.failNotEquals(Assert.java:776)\r\n\tat org.testng.Assert.assertTrue(Assert.java:44)\r\n\tat org.testng.Assert.assertTrue(Assert.java:54)\r\n\tat com.Test.EO.StepDefinitions.should_redirect_to_customer_Info_page(StepDefinitions.java:56)\r\n\tat ✽.Then should redirect to customer Info page(customerInfo.feature:8)\r\n",
              "status": "failed"
            },
            "line": 8,
            "name": "should redirect to customer Info page",
            "match": {
              "location": "StepDefinitions.should_redirect_to_customer_Info_page()"
            },
            "keyword": "Then "
          }
        ]
      }
    ],
    "name": "Test customer details",
    "description": "",
    "id": "test-customer-details",
    "keyword": "Feature",
    "uri": "customerInfo.feature"
  },
  {
    "line": 1,
    "elements": [
      {
        "line": 4,
        "name": "check emp details",
        "description": "",
        "id": "test-emp-details;check-emp-details",
        "type": "scenario",
        "keyword": "Scenario",
        "steps": [
          {
            "result": {
              "duration": 17300,
              "status": "passed"
            },
            "line": 5,
            "name": "open emp_deatils Page",
            "match": {
              "location": "StepDefinitions.open_emp_deatils_Page()"
            },
            "keyword": "Given "
          },
          {
            "result": {
              "duration": 15300,
              "status": "passed"
            },
            "line": 7,
            "name": "click on emp_Info button",
            "match": {
              "location": "StepDefinitions.click_on_emp_Info_button()"
            },
            "keyword": "When "
          },
          {
            "result": {
              "duration": 196500,
              "error_message": "java.lang.AssertionError: expected [toni] but found [tonny]\r\n\tat org.testng.Assert.fail(Assert.java:96)\r\n\tat org.testng.Assert.failNotEquals(Assert.java:776)\r\n\tat org.testng.Assert.assertEqualsImpl(Assert.java:137)\r\n\tat org.testng.Assert.assertEquals(Assert.java:118)\r\n\tat org.testng.Assert.assertEquals(Assert.java:453)\r\n\tat org.testng.Assert.assertEquals(Assert.java:463)\r\n\tat com.Test.EO.StepDefinitions.should_redirect_to_emp_Info_page(StepDefinitions.java:84)\r\n\tat ✽.Then should redirect to emp Info page(employee_details.feature:8)\r\n",
              "status": "failed"
            },
            "line": 8,
            "name": "should redirect to emp Info page",
            "match": {
              "location": "StepDefinitions.should_redirect_to_emp_Info_page()"
            },
            "keyword": "Then "
          }
        ]
      }
    ],
    "name": "Test emp details",
    "description": "",
    "id": "test-emp-details",
    "keyword": "Feature",
    "uri": "employee_details.feature"
  },
  {
    "line": 1,
    "elements": [
      {
        "line": 4,
        "name": "check Product details",
        "description": "",
        "id": "test-product-info;check-product-details",
        "type": "scenario",
        "keyword": "Scenario",
        "steps": [
          {
            "result": {
              "duration": 28600,
              "status": "passed"
            },
            "line": 5,
            "name": "open Product_deatils Page",
            "match": {
              "location": "StepDefinitions.open_Product_deatils_Page()"
            },
            "keyword": "Given "
          },
          {
            "result": {
              "duration": 16100,
              "status": "passed"
            },
            "line": 7,
            "name": "click on Product_Info button",
            "match": {
              "location": "StepDefinitions.click_on_Product_Info_button()"
            },
            "keyword": "When "
          },
          {
            "result": {
              "duration": 20600,
              "status": "passed"
            },
            "line": 8,
            "name": "should redirect to Product Info page",
            "match": {
              "location": "StepDefinitions.should_redirect_to_Product_Info_page()"
            },
            "keyword": "Then "
          }
        ]
      }
    ],
    "name": "Test Product Info",
    "description": "",
    "id": "test-product-info",
    "keyword": "Feature",
    "uri": "product_info.feature"
  },
  {
    "line": 1,
    "elements": [
      {
        "line": 4,
        "name": "check student details",
        "description": "",
        "id": "test-student-details;check-student-details",
        "type": "scenario",
        "keyword": "Scenario",
        "steps": [
          {
            "result": {
              "duration": 49400,
              "status": "passed"
            },
            "line": 5,
            "name": "open student_deatils Page",
            "match": {
              "location": "StepDefinitions.open_student_deatils_Page()"
            },
            "keyword": "Given "
          },
          {
            "result": {
              "duration": 19800,
              "status": "passed"
            },
            "line": 7,
            "name": "click on student_Info button",
            "match": {
              "location": "StepDefinitions.click_on_student_Info_button()"
            },
            "keyword": "When "
          },
          {
            "result": {
              "duration": 23200,
              "status": "passed"
            },
            "line": 8,
            "name": "should redirect to student Info page",
            "match": {
              "location": "StepDefinitions.should_redirect_to_student_Info_page()"
            },
            "keyword": "Then "
          }
        ]
      }
    ],
    "name": "Test student details",
    "description": "",
    "id": "test-student-details",
    "keyword": "Feature",
    "uri": "student_info.feature"
  },
  {
    "line": 1,
    "elements": [
      {
        "line": 4,
        "name": "check user details",
        "description": "",
        "id": "test-user-details;check-user-details",
        "type": "scenario",
        "keyword": "Scenario",
        "steps": [
          {
            "result": {
              "duration": 40400,
              "status": "passed"
            },
            "line": 5,
            "name": "open user_deatils Page",
            "match": {
              "location": "StepDefinitions.open_user_deatils_Page()"
            },
            "keyword": "Given "
          },
          {
            "result": {
              "duration": 13500,
              "status": "passed"
            },
            "line": 7,
            "name": "click on user_Info button",
            "match": {
              "location": "StepDefinitions.click_on_user_Info_button()"
            },
            "keyword": "When "
          },
          {
            "result": {
              "duration": 119200,
              "error_message": "org.testng.SkipException: skipped\r\n\tat com.Test.EO.StepDefinitions.should_redirect_to_user_Info_page(StepDefinitions.java:41)\r\n\tat ✽.Then should redirect to user Info page(user_Info.feature:8)\r\n",
              "status": "failed"
            },
            "line": 8,
            "name": "should redirect to user Info page",
            "match": {
              "location": "StepDefinitions.should_redirect_to_user_Info_page()"
            },
            "keyword": "Then "
          }
        ]
      }
    ],
    "name": "Test user details",
    "description": "",
    "id": "test-user-details",
    "keyword": "Feature",
    "uri": "user_Info.feature"
  }
]